functions_by_rybitska/README.md
functions_by_rybitska/math_functions.py
functions_by_rybitska-0.3.0.dist-info/WHEEL
functions_by_rybitska-0.3.0.dist-info/METADATA
functions_by_rybitska-0.3.0.dist-info/RECORD
