Metadata-Version: 2.1
Name: functions-by-rybitska
Version: 0.3.0
Summary: This is test project
Author: Khrystyna Rybitska
Author-email: krybitska@gmail.com
Requires-Python: >=3.10,<4.0
Classifier: Programming Language :: Python :: 3
Classifier: Programming Language :: Python :: 3.10
Classifier: Programming Language :: Python :: 3.11
